eprints2bags/__init__.py
eprints2bags/__main__.py
eprints2bags/constants.py
eprints2bags/eprints.py
eprints2bags/exceptions.py
eprints2bags/exit_codes.py
eprints2bags/files.py
eprints2bags/network.py
eprints2bags-1.10.3.data/scripts/eprints2bags
eprints2bags-1.10.3.dist-info/LICENSE
eprints2bags-1.10.3.dist-info/METADATA
eprints2bags-1.10.3.dist-info/WHEEL
eprints2bags-1.10.3.dist-info/top_level.txt
eprints2bags-1.10.3.dist-info/RECORD
