Metadata-Version: 2.1
Name: eprints2bags
Version: 1.10.3
Summary: Download EPrints content and save it in BagIt-format bags.
Home-page: https://github.com/caltechlibrary/eprints2bags
Author: Michael Hucka
Author-email: mhucka@caltech.edu
License: BSD 3-clause
Project-URL: Source Code, https://github.com/caltechlibrary/eprints2bags
Project-URL: Bug Tracker, https://github.com/caltechlibrary/eprints2bags/issues
Keywords: EPrints,archives,preservation,BagIt
Classifier: Development Status :: 5 - Production/Stable
Classifier: Environment :: Console
Classifier: Intended Audience :: Science/Research
Classifier: Intended Audience :: Information Technology
Classifier: Intended Audience :: System Administrators
Classifier: License :: OSI Approved :: BSD License
Classifier: Operating System :: MacOS :: MacOS X
Classifier: Operating System :: Microsoft :: Windows
Classifier: Operating System :: POSIX
Classifier: Operating System :: POSIX :: Linux
Classifier: Operating System :: Unix
Classifier: Programming Language :: Python
Classifier: Programming Language :: Python :: 3.5
Classifier: Topic :: System :: Archiving
Classifier: Topic :: System :: Archiving :: Packaging
Classifier: Topic :: Utilities
Requires-Python: >=3.5
License-File: LICENSE
Requires-Dist: aenum (>=3.1.0)
Requires-Dist: bagit (>=1.8.1)
Requires-Dist: bun (==0.0.8)
Requires-Dist: commonpy (>=1.9.1)
Requires-Dist: dateparser (>=0.7.0)
Requires-Dist: humanize (>=0.5.1)
Requires-Dist: keyring (>=12.2.0)
Requires-Dist: keyrings.alt (>=3.1)
Requires-Dist: lxml (>=4.2.5)
Requires-Dist: plac (>=1.0.0)
Requires-Dist: psutil (>=5.4)
Requires-Dist: pypubsub (>=4.0.0)
Requires-Dist: requests (>=2.19.1)
Requires-Dist: rich (>=5.2.0)
Requires-Dist: setuptools (>=41.0.1)
Requires-Dist: sidetrack (>=1.0.0)
Requires-Dist: urllib3 (>=1.23)
Requires-Dist: validators (>=0.12.3)
